MANIFEST.in
README.md
changes.txt
setup.py
zopen/__init__.py
zopen.frs.egg-info/PKG-INFO
zopen.frs.egg-info/SOURCES.txt
zopen.frs.egg-info/dependency_links.txt
zopen.frs.egg-info/entry_points.txt
zopen.frs.egg-info/namespace_packages.txt
zopen.frs.egg-info/not-zip-safe
zopen.frs.egg-info/requires.txt
zopen.frs.egg-info/top_level.txt
zopen/frs/__init__.py
zopen/frs/archive.py
zopen/frs/cache.py
zopen/frs/config.py
zopen/frs/frs.py
zopen/frs/recycle.py
zopen/frs/utils.py