Metadata-Version: 1.1
Name: zopen.frs
Version: 1.2.1
Summary: zopen frs management
Home-page: http://pypi.zopen.cn/zopen.frs
Author: panjy
Author-email: panjunyong@gmail.com
License: Private
Keywords: zope3 z3c rpc server client operation
Platform: UNKNOWN
Classifier: Environment :: Web Environment
Classifier: Intended Audience :: Developers
Classifier: Programming Language :: Python
Classifier: Operating System :: OS Independent
Classifier: Topic :: Internet :: WWW/HTTP
